generate_fastapi/__init__.py
generate_fastapi/version.py
generate_fastapi/file_generators/__init__.py
generate_fastapi/file_generators/fastapi_generator.py
generate_fastapi/mako_templates/migrations/script.py.mako
generate_fastapi/mako_templates/migrations/versions/added_routes/downgrade.sql
generate_fastapi/mako_templates/migrations/versions/added_routes/upgrade.sql
generate_fastapi/mako_templates/src/project/template_project_init.py
generate_fastapi/mako_templates/src/project/core/service_factory.py
generate_fastapi/mako_templates/src/project/domain/template_base_schemas.py
generate_fastapi/mako_templates/src/project/domain/model/template_model.py
generate_fastapi/mako_templates/src/project/domain/model/template_queries.py
generate_fastapi/mako_templates/src/project/domain/model/template_schemas.py
generate_fastapi/mako_templates/src/project/domain/model/template_services.py
generate_fastapi/mako_templates/src/project/routers/template_route.py
generate_fastapi/mako_templates/tests/conftest.py
generate_fastapi/mako_templates/tests/utils.py
generate_fastapi/mako_templates/tests/test_route/__init__.py
generate_fastapi/mako_templates/tests/test_route/test_basic_positive.py
generate_fastapi/mako_templates/tests/test_route/test_destructive.py
generate_fastapi/mako_templates/tests/test_route/test_extended_positive.py
generate_fastapi/mako_templates/tests/test_route/test_invalid_input_negative.py
generate_fastapi/mako_templates/tests/test_route/test_valid_input_negative.py
generate_fastapi/parsers/__init__.py
generate_fastapi/parsers/json_parser.py
generate_fastapi/parsers/sql_parser.py
generate_fastapi/schemas/__init__.py
generate_fastapi/schemas/baseschemas.py
generate_fastapi/translators/__init__.py
generate_fastapi/translators/json_translator.py
generate_fastapi/translators/sql_translator.py
generate_fastapi-0.1.3.dist-info/LICENSE
generate_fastapi-0.1.3.dist-info/METADATA
generate_fastapi-0.1.3.dist-info/WHEEL
generate_fastapi-0.1.3.dist-info/entry_points.txt
generate_fastapi-0.1.3.dist-info/top_level.txt
generate_fastapi-0.1.3.dist-info/RECORD
