Metadata-Version: 2.1
Name: generate-fastapi
Version: 0.1.3
Summary: REST API for generate_fastapi
Home-page: https://github.com/nymann/generate-fastapi
Maintainer: Kristian Nymann Jakobsen
Maintainer-email: kristian@nymann.dev
License: GPL v3
Platform: UNKNOWN
Requires-Python: >=3.8
Requires-Dist: sql-column-parser
Requires-Dist: typer
Requires-Dist: mako
Requires-Dist: requests
Requires-Dist: git-python
Provides-Extra: dev
Requires-Dist: wemake-python-styleguide ; extra == 'dev'
Requires-Dist: mypy ; extra == 'dev'
Requires-Dist: dlint ; extra == 'dev'
Requires-Dist: nitpick ; extra == 'dev'
Requires-Dist: cohesion ; extra == 'dev'
Requires-Dist: pyformat ; extra == 'dev'
